kes/__init__.py
kes/client.py
kes/project.py
kes/py.typed
kes/table.py
kes/fields/__init__.py
kes/fields/field.py
kes/fields/imagefield.py
kes/fields/locationfield.py
kes/proto/__init__.py
kes/proto/project_pb2.py
kes/proto/project_pb2.pyi
kes/proto/project_pb2_grpc.py
kes/proto/project_pb2_grpc.pyi
kes/proto/table_pb2.py
kes/proto/table_pb2.pyi
kes/proto/table_pb2_grpc.py
kes/proto/table_pb2_grpc.pyi
kes_RHDHV-1.dev14.dist-info/LICENSE
kes_RHDHV-1.dev14.dist-info/METADATA
kes_RHDHV-1.dev14.dist-info/WHEEL
kes_RHDHV-1.dev14.dist-info/top_level.txt
kes_RHDHV-1.dev14.dist-info/RECORD
