Metadata-Version: 2.1
Name: kes-RHDHV
Version: 1.dev14
Summary: KES python client
Home-page: https://github.com/RoyalHaskoningDHV/kes-python-client
Author: RoyalHaskoningDHV
Author-email: roel.de.jong@rhdhv.com
Project-URL: Bug Tracker, https://github.com/RoyalHaskoningDHV/kes-python-client/issues
Classifier: Programming Language :: Python :: 3
Classifier: License :: OSI Approved :: MIT License
Classifier: Operating System :: OS Independent
Requires-Python: >=3.10
License-File: LICENSE
Requires-Dist: mypy >=0.910
Requires-Dist: types-protobuf >=0.1.14
Requires-Dist: grpcio
Requires-Dist: protobuf <5,>=4.21.1
Requires-Dist: grpc-stubs
